jello/__init__.py
jello/__main__.py
jello/cli.py
jello/dotmap.py
jello/lib.py
jello-1.6.1.dist-info/LICENSE
jello-1.6.1.dist-info/METADATA
jello-1.6.1.dist-info/WHEEL
jello-1.6.1.dist-info/entry_points.txt
jello-1.6.1.dist-info/top_level.txt
jello-1.6.1.dist-info/RECORD
