Metadata-Version: 2.1
Name: jello
Version: 1.6.1
Summary: Filter JSON and JSON Lines data with Python syntax.
Home-page: https://github.com/kellyjonbrazil/jello
Author: Kelly Brazil
Author-email: kellyjonbrazil@gmail.com
License: MIT
Classifier: Programming Language :: Python :: 3
Classifier: License :: OSI Approved :: MIT License
Classifier: Operating System :: OS Independent
Classifier: Topic :: Utilities
Requires-Python: >=3.6
License-File: LICENSE
Requires-Dist: Pygments >=2.4.2
